cased/__init__.py
cased/__init__.py-e
cased/__init__.py-e-e
cased/api/__init__.py
cased/api/__init__.py-e
cased/api/__init__.py-e-e
cased/api/event.py
cased/api/event.py-e
cased/api/event.py-e-e
cased/api/export.py
cased/api/export.py-e
cased/api/export.py-e-e
cased/api/policy.py
cased/api/policy.py-e
cased/api/policy.py-e-e
cased/api/abstract/__init__.py
cased/api/abstract/__init__.py-e
cased/api/abstract/__init__.py-e-e
cased/api/abstract/api_resource.py
cased/api/abstract/api_resource.py-e
cased/api/abstract/api_resource.py-e-e
cased/api/abstract/creatable.py
cased/api/abstract/creatable.py-e
cased/api/abstract/creatable.py-e-e
cased/api/abstract/deletable.py
cased/api/abstract/deletable.py-e
cased/api/abstract/deletable.py-e-e
cased/api/abstract/listable.py
cased/api/abstract/listable.py-e
cased/api/abstract/listable.py-e-e
cased/api/abstract/results_list.py
cased/api/abstract/results_list.py-e
cased/api/abstract/results_list.py-e-e
cased/api/abstract/updateable.py
cased/api/abstract/updateable.py-e
cased/api/abstract/updateable.py-e-e
cased/data/__init__.py
cased/data/__init__.py-e
cased/data/__init__.py-e-e
cased/data/context.py
cased/data/query.py
cased/data/query.py-e
cased/data/query.py-e-e
cased/data/reliability.py
cased/data/reliability.py-e
cased/data/reliability.py-e-e
cased/data/sensitive.py
cased/data/sensitive.py-e
cased/data/sensitive.py-e-e
cased/errors/__init__.py
cased/errors/__init__.py-e
cased/errors/__init__.py-e-e
cased/http/__init__.py
cased/http/__init__.py-e
cased/http/__init__.py-e-e
cased/http/httpclient.py
cased/http/httpclient.py-e
cased/http/httpclient.py-e-e
cased/http/requestor.py
cased/http/requestor.py-e
cased/http/requestor.py-e-e
cased/plugins/__init__.py
cased/plugins/__init__.py-e
cased/plugins/__init__.py-e-e
cased/plugins/casedplugin.py
cased/plugins/casedplugin.py-e
cased/plugins/casedplugin.py-e-e
cased/tests/__init__.py
cased/tests/__init__.py-e
cased/tests/__init__.py-e-e
cased/tests/test_abstract.py
pycased-0.4.0.dist-info/LICENSE
pycased-0.4.0.dist-info/METADATA
pycased-0.4.0.dist-info/WHEEL
pycased-0.4.0.dist-info/top_level.txt
pycased-0.4.0.dist-info/RECORD
